soft_fido2/__init__.py
soft_fido2/__main__.py
soft_fido2/authenticator.py
soft_fido2/cable.py
soft_fido2/cert_utils.py
soft_fido2/credential_id_migrator.py
soft_fido2/hid_device.py
soft_fido2/key_pair.py
soft_fido2/message_queues.py
soft_fido2/passkey_device.py
soft_fido2/symmetric_key.py
soft_fido2/systray_app.py
soft_fido2/uhid_device.py
soft_fido2/usb_ip.py
soft_fido2-0.3.8.dist-info/licenses/LICENSE
soft_fido2-0.3.8.dist-info/METADATA
soft_fido2-0.3.8.dist-info/WHEEL
soft_fido2-0.3.8.dist-info/top_level.txt
soft_fido2-0.3.8.dist-info/RECORD
