Metadata-Version: 2.4
Name: soft_fido2
Version: 0.3.8
Summary: Software FIDO2 Passkey Authenticator
Home-page: https://github.com/lachlan-ibm/soft-fido2
Author: Lachlan Gleeson
Author-email: lgleeson@au1.ibm.com
License: MIT
Project-URL: Homepage, https://github.com/lachlan-ibm/soft-fido2
Project-URL: Documentation, https://github.com/lachlan-ibm/soft-fido2/README.md
Project-URL: Source, https://github.com/lachlan-ibm/soft-fido2
Project-URL: Tracker, https://github.com/lachlan-ibm/soft-fido2/issues
License-File: LICENSE
Requires-Dist: cbor2>=4.1.2
Requires-Dist: cryptography>=38.0.1
Requires-Dist: asn1>=2.2.0
Requires-Dist: PyJwt>=0.6.1
Dynamic: author
Dynamic: author-email
Dynamic: description
Dynamic: description-content-type
Dynamic: home-page
Dynamic: license
Dynamic: license-file
Dynamic: project-url
Dynamic: requires-dist
Dynamic: summary
